{
  "unversionedId": "app/info",
  "id": "app/info",
  "isDocsHomePage": false,
  "title": "B4LL Application",
  "description": "Our team is currently working in a mobile application to bring you new",
  "source": "@site/docs/app/info.md",
  "slug": "/app/info",
  "permalink": "/b4ll-docs/docs/app/info",
  "version": "current",
  "sidebar_label": "Info",
  "sidebar": "someSidebar",
  "previous": {
    "title": "Call Centre Enrolment",
    "permalink": "/b4ll-docs/docs/voice/callcentre"
  },
  "next": {
    "title": "Quick Guide",
    "permalink": "/b4ll-docs/docs/manual/quickguide"
  }
}